{"A": ["a1", "a2"], "H": "[{\"frozenset()\": 0.0, \"frozenset({'a1'})\": 1.657860042238787, \"frozenset({'a2'})\": 1.7468356889552359, \"frozenset({'a2', 'a1'})\": 2.6825816272326315}, {\"frozenset()\": 0.0, \"frozenset({'a1'})\": 2.398539807754551, \"frozenset({'a2'})\": 2.1807825076493144, \"frozenset({'a2', 'a1'})\": 0.8254189972800476}, {\"frozenset()\": 0.0, \"frozenset({'a1'})\": -0.17546334567622535, \"frozenset({'a2'})\": -0.7923446229224054, \"frozenset({'a2', 'a1'})\": 0.4454123423456795}, {\"frozenset()\": 0.0, \"frozenset({'a1'})\": 1.2749004996473996, \"frozenset({'a2'})\": 2.3962662286421343, \"frozenset({'a2', 'a1'})\": 4.617844179246753}, {\"frozenset()\": 0.0, \"frozenset({'a1'})\": 0.07894310136120153, \"frozenset({'a2'})\": 0.23756316629829322, \"frozenset({'a2', 'a1'})\": 2.679953381258601}, {\"frozenset()\": 0.0, \"frozenset({'a1'})\": -0.05992535155796874, \"frozenset({'a2'})\": 0.8405793314089638, \"frozenset({'a2', 'a1'})\": 2.689740864471507}]", "Pi": "[{\"py/tuple\": [{\"py/object\": \"networkx.classes.graph.Graph\", \"graph_attr_dict_factory\": {\"py/type\": \"builtins.dict\"}, \"node_dict_factory\": {\"py/type\": \"builtins.dict\"}, \"node_attr_dict_factory\": {\"py/type\": \"builtins.dict\"}, \"adjlist_outer_dict_factory\": {\"py/type\": \"builtins.dict\"}, \"adjlist_inner_dict_factory\": {\"py/type\": \"builtins.dict\"}, \"edge_attr_dict_factory\": {\"py/type\": \"builtins.dict\"}, \"graph\": {}, \"_node\": {\"a1\": {}, \"a2\": {}}, \"_adj\": {\"a1\": {}, \"a2\": {}}}, {\"py/set\": [\"a1\"]}, {\"a1\": 1}, {\"a1\": 0}, 1, 0]}, {\"py/tuple\": [{\"py/object\": \"networkx.classes.graph.Graph\", \"graph_attr_dict_factory\": {\"py/type\": \"builtins.dict\"}, \"node_dict_factory\": {\"py/type\": \"builtins.dict\"}, \"node_attr_dict_factory\": {\"py/type\": \"builtins.dict\"}, \"adjlist_outer_dict_factory\": {\"py/type\": \"builtins.dict\"}, \"adjlist_inner_dict_factory\": {\"py/type\": \"builtins.dict\"}, \"edge_attr_dict_factory\": {\"py/type\": \"builtins.dict\"}, \"graph\": {}, \"_node\": {\"a1\": {}, \"a2\": {}}, \"_adj\": {\"a1\": {}, \"a2\": {}}}, {\"py/set\": [\"a2\"]}, {\"a2\": 1}, {\"a2\": 0}, 1, 0]}, {\"py/tuple\": [{\"py/object\": \"networkx.classes.graph.Graph\", \"graph_attr_dict_factory\": {\"py/type\": \"builtins.dict\"}, \"node_dict_factory\": {\"py/type\": \"builtins.dict\"}, \"node_attr_dict_factory\": {\"py/type\": \"builtins.dict\"}, \"adjlist_outer_dict_factory\": {\"py/type\": \"builtins.dict\"}, \"adjlist_inner_dict_factory\": {\"py/type\": \"builtins.dict\"}, \"edge_attr_dict_factory\": {\"py/type\": \"builtins.dict\"}, \"graph\": {}, \"_node\": {\"a1\": {}, \"a2\": {}}, \"_adj\": {\"a1\": {\"a2\": {}}, \"a2\": {\"a1\": {\"py/id\": 28}}}}, {\"py/set\": []}, {}, {}, 1, 0]}, {\"py/tuple\": [{\"py/object\": \"networkx.classes.graph.Graph\", \"graph_attr_dict_factory\": {\"py/type\": \"builtins.dict\"}, \"node_dict_factory\": {\"py/type\": \"builtins.dict\"}, \"node_attr_dict_factory\": {\"py/type\": \"builtins.dict\"}, \"adjlist_outer_dict_factory\": {\"py/type\": \"builtins.dict\"}, \"adjlist_inner_dict_factory\": {\"py/type\": \"builtins.dict\"}, \"edge_attr_dict_factory\": {\"py/type\": \"builtins.dict\"}, \"graph\": {}, \"_node\": {\"a1\": {}, \"a2\": {}}, \"_adj\": {\"a1\": {\"a2\": {}}, \"a2\": {\"a1\": {\"py/id\": 39}}}}, {\"py/set\": []}, {}, {}, 1, 0]}, {\"py/tuple\": [{\"py/object\": \"networkx.classes.graph.Graph\", \"graph_attr_dict_factory\": {\"py/type\": \"builtins.dict\"}, \"node_dict_factory\": {\"py/type\": \"builtins.dict\"}, \"node_attr_dict_factory\": {\"py/type\": \"builtins.dict\"}, \"adjlist_outer_dict_factory\": {\"py/type\": \"builtins.dict\"}, \"adjlist_inner_dict_factory\": {\"py/type\": \"builtins.dict\"}, \"edge_attr_dict_factory\": {\"py/type\": \"builtins.dict\"}, \"graph\": {}, \"_node\": {\"a1\": {}, \"a2\": {}}, \"_adj\": {\"a1\": {\"a2\": {}}, \"a2\": {\"a1\": {\"py/id\": 50}}}}, {\"py/set\": []}, {}, {}, 1, 0]}, {\"py/tuple\": [{\"py/object\": \"networkx.classes.graph.Graph\", \"graph_attr_dict_factory\": {\"py/type\": \"builtins.dict\"}, \"node_dict_factory\": {\"py/type\": \"builtins.dict\"}, \"node_attr_dict_factory\": {\"py/type\": \"builtins.dict\"}, \"adjlist_outer_dict_factory\": {\"py/type\": \"builtins.dict\"}, \"adjlist_inner_dict_factory\": {\"py/type\": \"builtins.dict\"}, \"edge_attr_dict_factory\": {\"py/type\": \"builtins.dict\"}, \"graph\": {}, \"_node\": {\"a1\": {}, \"a2\": {}}, \"_adj\": {\"a1\": {\"a2\": {}}, \"a2\": {\"a1\": {\"py/id\": 61}}}}, {\"py/set\": [\"a2\"]}, {\"a2\": 1}, {\"a2\": 0}, 1, 0]}]"}